[
  {
    "title": "American Chopper 2: Full Throttle",
    "url": "/wiki/American_Chopper_2:_Full_Throttle",
    "year": 2005,
    "month": 11,
    "day": 29,
    "systems": [
      "Gamecube"
    ]
  },
  {
    "title": "Animaniacs: The Great Edgar Hunt",
    "url": "/wiki/Animaniacs:_The_Great_Edgar_Hunt",
    "year": 2005,
    "month": 9,
    "day": 18,
    "systems": [
      "Gamecube"
    ]
  },
  {
    "title": "Battalion Wars",
    "url": "/wiki/Battalion_Wars",
    "year": 2005,
    "month": 9,
    "day": 19,
    "systems": [
      "Gamecube"
    ]
  },
  {
    "title": "Bratz: Rock Angelz",
    "url": "/wiki/Bratz:_Rock_Angelz_(video_game)",
    "year": 2005,
    "month": 10,
    "day": 5,
    "systems": [
      "Gamecube"
    ]
  },
  {
    "title": "Cabela's Outdoor Adventures",
    "url": "/wiki/Cabela%27s_Outdoor_Adventures",
    "year": 2005,
    "month": 9,
    "day": 13,
    "systems": [
      "Gamecube"
    ]
  },
  {
    "title": "Chaos Field",
    "url": "/wiki/Chaos_Field",
    "year": 2005,
    "month": 12,
    "day": 20,
    "systems": [
      "Gamecube"
    ]
  },
  {
    "title": "Charlie and the Chocolate Factory",
    "url": "/wiki/Charlie_and_the_Chocolate_Factory_(2005_video_game)",
    "year": 2005,
    "month": 7,
    "day": 11,
    "systems": [
      "Gamecube"
    ]
  },
  {
    "title": "Chicken Little",
    "url": "/wiki/Chicken_Little_(video_game)",
    "year": 2005,
    "month": 10,
    "day": 20,
    "systems": [
      "Gamecube"
    ]
  },
  {
    "title": "Codename: Kids Next Door – Operation: V.I.D.E.O.G.A.M.E.",
    "url": "/wiki/Codename:_Kids_Next_Door_%E2%80%93_Operation:_V.I.D.E.O.G.A.M.E.",
    "year": 2005,
    "month": 10,
    "day": 11,
    "systems": [
      "Gamecube"
    ]
  },
  {
    "title": "Dance Dance Revolution Mario Mix",
    "url": "/wiki/Dance_Dance_Revolution_Mario_Mix",
    "year": 2005,
    "month": 10,
    "day": 24,
    "systems": [
      "Gamecube"
    ]
  },
  {
    "title": "Digimon World 4",
    "url": "/wiki/Digimon_World_4",
    "year": 2005,
    "month": 6,
    "day": 1,
    "systems": [
      "Gamecube"
    ]
  },
  {
    "title": "Donkey Kong Jungle Beat",
    "url": "/wiki/Donkey_Kong_Jungle_Beat",
    "year": 2005,
    "month": 3,
    "day": 14,
    "systems": [
      "Gamecube"
    ]
  },
  {
    "title": "Donkey Konga 2",
    "url": "/wiki/Donkey_Konga_2",
    "year": 2005,
    "month": 5,
    "day": 9,
    "systems": [
      "Gamecube"
    ]
  },
  {
    "title": "Dora the Explorer: Journey to the Purple Planet",
    "url": "/wiki/Dora_the_Explorer:_Journey_to_the_Purple_Planet",
    "year": 2005,
    "month": 10,
    "day": 13,
    "systems": [
      "Gamecube"
    ]
  },
  {
    "title": "FIFA Soccer 06",
    "url": "/wiki/FIFA_06",
    "year": 2005,
    "month": 10,
    "day": 4,
    "systems": [
      "Gamecube"
    ]
  },
  {
    "title": "Fire Emblem: Path of Radiance",
    "url": "/wiki/Fire_Emblem:_Path_of_Radiance",
    "year": 2005,
    "month": 10,
    "day": 17,
    "systems": [
      "Gamecube"
    ]
  },
  {
    "title": "Frogger: Ancient Shadow",
    "url": "/wiki/Frogger:_Ancient_Shadow",
    "year": 2005,
    "month": 9,
    "day": 27,
    "systems": [
      "Gamecube"
    ]
  },
  {
    "title": "From Russia with Love",
    "url": "/wiki/James_Bond_007:_From_Russia_with_Love",
    "year": 2005,
    "month": 11,
    "day": 15,
    "systems": [
      "Gamecube"
    ]
  },
  {
    "title": "Geist",
    "url": "/wiki/Geist_(video_game)",
    "year": 2005,
    "month": 8,
    "day": 15,
    "systems": [
      "Gamecube"
    ]
  },
  {
    "title": "GUN",
    "url": "/wiki/Gun_(video_game)",
    "year": 2005,
    "month": 11,
    "day": 8,
    "systems": [
      "Gamecube"
    ]
  },
  {
    "title": "Harvest Moon: Another Wonderful Life",
    "url": "/wiki/Harvest_Moon:_Another_Wonderful_Life",
    "year": 2005,
    "month": 7,
    "day": 26,
    "systems": [
      "Gamecube"
    ]
  },
  {
    "title": "Hello Kitty: Roller Rescue",
    "url": "/wiki/Hello_Kitty:_Roller_Rescue",
    "year": 2005,
    "month": 8,
    "day": 16,
    "systems": [
      "Gamecube"
    ]
  },
  {
    "title": "Killer7",
    "url": "/wiki/Killer7",
    "year": 2005,
    "month": 7,
    "day": 7,
    "systems": [
      "Gamecube"
    ]
  },
  {
    "title": "Lego Star Wars: The Video Game",
    "url": "/wiki/Lego_Star_Wars:_The_Video_Game",
    "year": 2005,
    "month": 10,
    "day": 25,
    "systems": [
      "Gamecube"
    ]
  },
  {
    "title": "Mario Party 7",
    "url": "/wiki/Mario_Party_7",
    "year": 2005,
    "month": 11,
    "day": 7,
    "systems": [
      "Gamecube"
    ]
  },
  {
    "title": "Mario Superstar Baseball",
    "url": "/wiki/Mario_Superstar_Baseball",
    "year": 2005,
    "month": 8,
    "day": 29,
    "systems": [
      "Gamecube"
    ]
  },
  {
    "title": "Mark Davis Pro Bass Challenge",
    "url": "/wiki/Mark_Davis_Pro_Bass_Challenge",
    "year": 2005,
    "month": 9,
    "day": 20,
    "systems": [
      "Gamecube"
    ]
  },
  {
    "title": "Midway Arcade Treasures 3",
    "url": "/wiki/Midway_Arcade_Treasures_3",
    "year": 2005,
    "month": 10,
    "day": 26,
    "systems": [
      "Gamecube"
    ]
  },
  {
    "title": "Mortal Kombat: Deception",
    "url": "/wiki/Mortal_Kombat:_Deception",
    "year": 2005,
    "month": 3,
    "day": 1,
    "systems": [
      "Gamecube"
    ]
  },
  {
    "title": "Nicktoons Unite!",
    "url": "/wiki/Nicktoons_Unite!",
    "year": 2005,
    "month": 10,
    "day": 27,
    "systems": [
      "Gamecube"
    ]
  },
  {
    "title": "One Piece: Grand Battle! Rush",
    "url": "/wiki/One_Piece:_Grand_Battle!_Rush",
    "year": 2005,
    "month": 9,
    "day": 7,
    "systems": [
      "Gamecube"
    ]
  },
  {
    "title": "Peter Jackson's King Kong: The Official Game of the Movie",
    "url": "/wiki/Peter_Jackson%27s_King_Kong:_The_Official_Game_of_the_Movie",
    "year": 2005,
    "month": 11,
    "day": 21,
    "systems": [
      "Gamecube"
    ]
  },
  {
    "title": "Pinball Hall of Fame: The Gottlieb Collection",
    "url": "/wiki/Pinball_Hall_of_Fame:_The_Gottlieb_Collection",
    "year": 2005,
    "month": 3,
    "day": 20,
    "systems": [
      "Gamecube"
    ]
  },
  {
    "title": "Pokémon XD: Gale of Darkness",
    "url": "/wiki/Pok%C3%A9mon_XD:_Gale_of_Darkness",
    "year": 2005,
    "month": 10,
    "day": 3,
    "systems": [
      "Gamecube"
    ]
  },
  {
    "title": "Rave Master",
    "url": "/wiki/Rave_Master_(video_game)",
    "year": 2005,
    "month": 3,
    "day": 8,
    "systems": [
      "Gamecube"
    ]
  },
  {
    "title": "Resident Evil 4",
    "url": "/wiki/Resident_Evil_4",
    "year": 2005,
    "month": 1,
    "day": 11,
    "systems": [
      "Gamecube"
    ]
  },
  {
    "title": "Sea World: Shamu's Deep Sea Adventures",
    "url": "/wiki/Sea_World:_Shamu%27s_Deep_Sea_Adventures",
    "year": 2005,
    "month": 11,
    "day": 8,
    "systems": [
      "Gamecube"
    ]
  },
  {
    "title": "Sonic Gems Collection",
    "url": "/wiki/Sonic_Gems_Collection",
    "year": 2005,
    "month": 8,
    "day": 16,
    "systems": [
      "Gamecube"
    ]
  },
  {
    "title": "SSX on Tour",
    "url": "/wiki/SSX_on_Tour",
    "year": 2005,
    "month": 10,
    "day": 11,
    "systems": [
      "Gamecube"
    ]
  },
  {
    "title": "Star Fox: Assault",
    "url": "/wiki/Star_Fox:_Assault",
    "year": 2005,
    "month": 2,
    "day": 14,
    "systems": [
      "Gamecube"
    ]
  },
  {
    "title": "Strike Force Bowling",
    "url": "/wiki/Strike_Force_Bowling",
    "year": 2005,
    "month": 3,
    "day": 20,
    "systems": [
      "Gamecube"
    ]
  },
  {
    "title": "Super Mario Strikers",
    "url": "/wiki/Super_Mario_Strikers",
    "year": 2005,
    "month": 12,
    "day": 5,
    "systems": [
      "Gamecube"
    ]
  },
  {
    "title": "TMNT: Mutant Melee",
    "url": "/wiki/TMNT:_Mutant_Melee",
    "year": 2005,
    "month": 3,
    "day": 16,
    "systems": [
      "Gamecube"
    ]
  },
  {
    "title": "Tom Clancy's Ghost Recon 2",
    "url": "/wiki/Tom_Clancy%27s_Ghost_Recon_2",
    "year": 2005,
    "month": 3,
    "day": 15,
    "systems": [
      "Gamecube"
    ]
  },
  {
    "title": "Tom Clancy's Rainbow Six: Lockdown",
    "url": "/wiki/Tom_Clancy%27s_Rainbow_Six:_Lockdown",
    "year": 2005,
    "month": 9,
    "day": 27,
    "systems": [
      "Gamecube"
    ]
  },
  {
    "title": "Ty the Tasmanian Tiger 3: Night of the Quinkan",
    "url": "/wiki/Ty_the_Tasmanian_Tiger_3:_Night_of_the_Quinkan",
    "year": 2005,
    "month": 10,
    "day": 12,
    "systems": [
      "Gamecube"
    ]
  },
  {
    "title": "Ultimate Spider-Man",
    "url": "/wiki/Ultimate_Spider-Man_(video_game)",
    "year": 2005,
    "month": 9,
    "day": 21,
    "systems": [
      "Gamecube"
    ]
  },
  {
    "title": "Viewtiful Joe: Red Hot Rumble",
    "url": "/wiki/Viewtiful_Joe:_Red_Hot_Rumble",
    "year": 2005,
    "month": 11,
    "day": 8,
    "systems": [
      "Gamecube"
    ]
  },
  {
    "title": "Virtua Quest",
    "url": "/wiki/Virtua_Quest",
    "year": 2005,
    "month": 1,
    "day": 19,
    "systems": [
      "Gamecube"
    ]
  },
  {
    "title": "Winnie the Pooh's Rumbly Tumbly Adventure",
    "url": "/wiki/Winnie_the_Pooh%27s_Rumbly_Tumbly_Adventure",
    "year": 2005,
    "month": 2,
    "day": 8,
    "systems": [
      "Gamecube"
    ]
  },
  {
    "title": "World Series of Poker",
    "url": "/wiki/World_Series_of_Poker_(video_game)",
    "year": 2005,
    "month": 9,
    "day": 14,
    "systems": [
      "Gamecube"
    ]
  },
  {
    "title": "WWE Day of Reckoning 2",
    "url": "/wiki/WWE_Day_of_Reckoning_2",
    "year": 2005,
    "month": 8,
    "day": 29,
    "systems": [
      "Gamecube"
    ]
  },
  {
    "title": "Zatch Bell! Mamodo Battles",
    "url": "/wiki/Zatch_Bell!_Mamodo_Battles",
    "year": 2005,
    "month": 10,
    "day": 19,
    "systems": [
      "Gamecube"
    ]
  },
  {
    "title": "007: From Russia with Love",
    "url": "/wiki/James_Bond_007:_From_Russia_with_Love",
    "year": 2005,
    "month": 11,
    "day": 1,
    "systems": [
      "Xbox"
    ]
  },
  {
    "title": "187 Ride or Die",
    "url": "/wiki/187_Ride_or_Die",
    "year": 2005,
    "month": 8,
    "day": 23,
    "systems": [
      "Xbox"
    ]
  },
  {
    "title": "50 Cent: Bulletproof",
    "url": "/wiki/50_Cent:_Bulletproof",
    "year": 2005,
    "month": 11,
    "day": 17,
    "systems": [
      "Xbox"
    ]
  },
  {
    "title": "Advent Rising",
    "url": "/wiki/Advent_Rising",
    "year": 2005,
    "month": 5,
    "day": 31,
    "systems": [
      "Xbox"
    ]
  },
  {
    "title": "Æon Flux",
    "url": "/wiki/%C3%86on_Flux_(video_game)",
    "year": 2005,
    "month": 11,
    "day": 15,
    "systems": [
      "Xbox"
    ]
  },
  {
    "title": "Alfa Romeo Racing Italiano",
    "url": "/wiki/Alfa_Romeo_Racing_Italiano",
    "year": 2005,
    "month": 6,
    "day": 24,
    "systems": [
      "Xbox"
    ]
  },
  {
    "title": "America's Army: Rise of a Soldier",
    "url": "/wiki/America%27s_Army:_Rise_of_a_Soldier",
    "year": 2005,
    "month": 11,
    "day": 17,
    "systems": [
      "Xbox"
    ]
  },
  {
    "title": "American Chopper 2: Full Throttle",
    "url": "/wiki/American_Chopper_2:_Full_Throttle",
    "year": 2005,
    "month": 11,
    "day": 17,
    "systems": [
      "Xbox"
    ]
  },
  {
    "title": "Animaniacs: The Great Edgar Hunt",
    "url": "/wiki/Animaniacs:_The_Great_Edgar_Hunt",
    "year": 2005,
    "month": 8,
    "day": 29,
    "systems": [
      "Xbox"
    ]
  },
  {
    "title": "Area 51",
    "url": "/wiki/Area_51_(first-person_shooter)",
    "year": 2005,
    "month": 4,
    "day": 25,
    "systems": [
      "Xbox"
    ]
  },
  {
    "title": "Batman Begins",
    "url": "/wiki/Batman_Begins_(video_game)",
    "year": 2005,
    "month": 6,
    "day": 14,
    "systems": [
      "Gamecube",
      "Xbox"
    ]
  },
  {
    "title": "Battlefield 2: Modern Combat",
    "url": "/wiki/Battlefield_2:_Modern_Combat",
    "year": 2005,
    "month": 10,
    "day": 24,
    "systems": [
      "Xbox"
    ]
  },
  {
    "title": "Beat Down: Fists of Vengeance",
    "url": "/wiki/Beat_Down:_Fists_of_Vengeance",
    "year": 2005,
    "month": 8,
    "day": 23,
    "systems": [
      "Xbox"
    ]
  },
  {
    "title": "The Bible Game",
    "url": "/wiki/The_Bible_Game",
    "year": 2005,
    "month": 10,
    "day": 23,
    "systems": [
      "Xbox"
    ]
  },
  {
    "title": "Big Mutha Truckers 2",
    "url": "/wiki/Big_Mutha_Truckers_2",
    "year": 2005,
    "month": 8,
    "day": 28,
    "systems": [
      "Xbox"
    ]
  },
  {
    "title": "Blitz: The League",
    "url": "/wiki/Blitz:_The_League",
    "year": 2005,
    "month": 10,
    "day": 17,
    "systems": [
      "Xbox"
    ]
  },
  {
    "title": "Breeders' Cup World Thoroughbred Championships",
    "url": "/wiki/Breeders%27_Cup_World_Thoroughbred_Championships",
    "year": 2005,
    "month": 9,
    "day": 29,
    "systems": [
      "Xbox"
    ]
  },
  {
    "title": "Brothers in Arms: Earned in Blood",
    "url": "/wiki/Brothers_in_Arms:_Earned_in_Blood",
    "year": 2005,
    "month": 10,
    "day": 4,
    "systems": [
      "Xbox"
    ]
  },
  {
    "title": "Brothers in Arms: Road to Hill 30",
    "url": "/wiki/Brothers_in_Arms:_Road_to_Hill_30",
    "year": 2005,
    "month": 3,
    "day": 1,
    "systems": [
      "Xbox"
    ]
  },
  {
    "title": "Burnout Revenge",
    "url": "/wiki/Burnout_Revenge",
    "year": 2005,
    "month": 9,
    "day": 13,
    "systems": [
      "Xbox"
    ]
  },
  {
    "title": "Cabela's Dangerous Hunts 2",
    "url": "/wiki/Cabela%27s_Dangerous_Hunts_2",
    "year": 2005,
    "month": 11,
    "day": 16,
    "systems": [
      "Gamecube",
      "Xbox"
    ]
  },
  {
    "title": "Cabela's Outdoor Adventures",
    "url": "/wiki/Cabela%27s_Outdoor_Adventures",
    "year": 2005,
    "month": 9,
    "day": 14,
    "systems": [
      "Xbox"
    ]
  },
  {
    "title": "Call of Cthulhu: Dark Corners of the Earth",
    "url": "/wiki/Call_of_Cthulhu:_Dark_Corners_of_the_Earth",
    "year": 2005,
    "month": 10,
    "day": 24,
    "systems": [
      "Xbox"
    ]
  },
  {
    "title": "Call of Duty 2: Big Red One",
    "url": "/wiki/Call_of_Duty_2:_Big_Red_One",
    "year": 2005,
    "month": 11,
    "day": 1,
    "systems": [
      "Gamecube",
      "Xbox"
    ]
  },
  {
    "title": "Capcom Classics Collection Vol. 1",
    "url": "/wiki/Capcom_Classics_Collection",
    "year": 2005,
    "month": 9,
    "day": 27,
    "systems": [
      "Xbox"
    ]
  },
  {
    "title": "Capcom Fighting Evolution",
    "url": "/wiki/Capcom_Fighting_Evolution",
    "year": 2005,
    "month": 6,
    "day": 14,
    "systems": [
      "Xbox"
    ]
  },
  {
    "title": "Castlevania: Curse of Darkness",
    "url": "/wiki/Castlevania:_Curse_of_Darkness",
    "year": 2005,
    "month": 11,
    "day": 5,
    "systems": [
      "Xbox"
    ]
  },
  {
    "title": "Charlie and the Chocolate Factory",
    "url": "/wiki/Charlie_and_the_Chocolate_Factory_(2005_video_game)",
    "year": 2005,
    "month": 7,
    "day": 15,
    "systems": [
      "Xbox"
    ]
  },
  {
    "title": "Chicago Enforcer",
    "url": "/wiki/Chicago_Enforcer",
    "year": 2005,
    "month": 2,
    "day": 23,
    "systems": [
      "Xbox"
    ]
  },
  {
    "title": "Chicken Little",
    "url": "/wiki/Chicken_Little_(video_game)",
    "year": 2005,
    "month": 10,
    "day": 18,
    "systems": [
      "Xbox"
    ]
  },
  {
    "title": "The Chronicles of Narnia: The Lion, the Witch and the Wardrobe",
    "url": "/wiki/The_Chronicles_of_Narnia:_The_Lion,_the_Witch_and_the_Wardrobe_(video_game)",
    "year": 2005,
    "month": 11,
    "day": 14,
    "systems": [
      "Gamecube",
      "Xbox"
    ]
  },
  {
    "title": "Classified: The Sentinel Crisis",
    "url": "/wiki/Classified:_The_Sentinel_Crisis",
    "year": 2005,
    "month": 5,
    "day": 25,
    "systems": [
      "Xbox"
    ]
  },
  {
    "title": "Close Combat: First to Fight",
    "url": "/wiki/Close_Combat:_First_to_Fight",
    "year": 2005,
    "month": 4,
    "day": 6,
    "systems": [
      "Xbox"
    ]
  },
  {
    "title": "Codename: Kids Next Door - Operation: V.I.D.E.O.G.A.M.E.",
    "url": "/wiki/Codename:_Kids_Next_Door_-_Operation:_V.I.D.E.O.G.A.M.E.",
    "year": 2005,
    "month": 10,
    "day": 11,
    "systems": [
      "Xbox"
    ]
  },
  {
    "title": "Cold Fear",
    "url": "/wiki/Cold_Fear",
    "year": 2005,
    "month": 3,
    "day": 15,
    "systems": [
      "Xbox"
    ]
  },
  {
    "title": "Cold War",
    "url": "/wiki/Cold_War_(video_game)",
    "year": 2005,
    "month": 9,
    "day": 27,
    "systems": [
      "Xbox"
    ]
  },
  {
    "title": "College Hoops 2K6",
    "url": "/wiki/College_Hoops_2K6",
    "year": 2005,
    "month": 11,
    "day": 1,
    "systems": [
      "Xbox"
    ]
  },
  {
    "title": "Combat Elite: WWII Paratroopers",
    "url": "/wiki/Combat_Elite:_WWII_Paratroopers",
    "year": 2005,
    "month": 11,
    "day": 21,
    "systems": [
      "Xbox"
    ]
  },
  {
    "title": "Combat: Task Force 121",
    "url": null,
    "year": 2005,
    "month": 3,
    "day": 22,
    "systems": [
      "Xbox"
    ]
  },
  {
    "title": "Conflict: Global Terror",
    "url": "/wiki/Conflict:_Global_Terror",
    "year": 2005,
    "month": 10,
    "day": 4,
    "systems": [
      "Xbox"
    ]
  },
  {
    "title": "Conker: Live & Reloaded",
    "url": "/wiki/Conker:_Live_%26_Reloaded",
    "year": 2005,
    "month": 6,
    "day": 21,
    "systems": [
      "Xbox"
    ]
  },
  {
    "title": "Constantine",
    "url": "/wiki/Constantine_(video_game)",
    "year": 2005,
    "month": 2,
    "day": 15,
    "systems": [
      "Xbox"
    ]
  },
  {
    "title": "Crash Tag Team Racing",
    "url": "/wiki/Crash_Tag_Team_Racing",
    "year": 2005,
    "month": 10,
    "day": 19,
    "systems": [
      "Gamecube",
      "Xbox"
    ]
  },
  {
    "title": "Crime Life: Gang Wars",
    "url": "/wiki/Crime_Life:_Gang_Wars",
    "year": 2005,
    "month": 11,
    "day": 22,
    "systems": [
      "Xbox"
    ]
  },
  {
    "title": "Dai Senryaku VII: Modern Military Tactics",
    "url": "/wiki/Dai_Senryaku_VII:_Modern_Military_Tactics",
    "year": 2005,
    "month": 2,
    "day": 15,
    "systems": [
      "Xbox"
    ]
  },
  {
    "title": "Dance Dance Revolution Ultramix 3",
    "url": "/wiki/Dance_Dance_Revolution_Ultramix_3",
    "year": 2005,
    "month": 11,
    "day": 15,
    "systems": [
      "Xbox"
    ]
  },
  {
    "title": "Darkwatch",
    "url": "/wiki/Darkwatch",
    "year": 2005,
    "month": 8,
    "day": 16,
    "systems": [
      "Xbox"
    ]
  },
  {
    "title": "Dead to Rights II",
    "url": "/wiki/Dead_to_Rights_II",
    "year": 2005,
    "month": 4,
    "day": 12,
    "systems": [
      "Xbox"
    ]
  },
  {
    "title": "Delta Force: Black Hawk Down",
    "url": "/wiki/Delta_Force:_Black_Hawk_Down",
    "year": 2005,
    "month": 7,
    "day": 26,
    "systems": [
      "Xbox"
    ]
  },
  {
    "title": "Destroy All Humans!",
    "url": "/wiki/Destroy_All_Humans!",
    "year": 2005,
    "month": 6,
    "day": 21,
    "systems": [
      "Xbox"
    ]
  },
  {
    "title": "Digimon World 4",
    "url": "/wiki/Digimon_World_4",
    "year": 2005,
    "month": 6,
    "day": 2,
    "systems": [
      "Xbox"
    ]
  },
  {
    "title": "Doom 3",
    "url": "/wiki/Doom_3",
    "year": 2005,
    "month": 4,
    "day": 3,
    "systems": [
      "Xbox"
    ]
  },
  {
    "title": "Doom 3: Resurrection of Evil",
    "url": "/wiki/Doom_3:_Resurrection_of_Evil",
    "year": 2005,
    "month": 10,
    "day": 5,
    "systems": [
      "Xbox"
    ]
  },
  {
    "title": "Dragon Ball Z: Sagas",
    "url": "/wiki/Dragon_Ball_Z:_Sagas",
    "year": 2005,
    "month": 3,
    "day": 22,
    "systems": [
      "Gamecube",
      "Xbox"
    ]
  },
  {
    "title": "Dynasty Warriors 5",
    "url": "/wiki/Dynasty_Warriors_5",
    "year": 2005,
    "month": 9,
    "day": 13,
    "systems": [
      "Xbox"
    ]
  },
  {
    "title": "Ed, Edd n Eddy: The Mis-Edventures",
    "url": "/wiki/Ed,_Edd_n_Eddy:_The_Mis-Edventures",
    "year": 2005,
    "month": 11,
    "day": 3,
    "systems": [
      "Gamecube",
      "Xbox"
    ]
  },
  {
    "title": "ESPN Major League Baseball",
    "url": null,
    "year": 2005,
    "month": 2,
    "day": 23,
    "systems": [
      "Xbox"
    ]
  },
  {
    "title": "Fable: The Lost Chapters",
    "url": "/wiki/Fable_(2004_video_game)",
    "year": 2005,
    "month": 10,
    "day": 18,
    "systems": [
      "Xbox"
    ]
  },
  {
    "title": "Fantastic 4",
    "url": "/wiki/Fantastic_Four_(2005_video_game)",
    "year": 2005,
    "month": 6,
    "day": 27,
    "systems": [
      "Gamecube",
      "Xbox"
    ]
  },
  {
    "title": "Far Cry Instincts",
    "url": "/wiki/Far_Cry_Instincts",
    "year": 2005,
    "month": 9,
    "day": 27,
    "systems": [
      "Xbox"
    ]
  },
  {
    "title": "FIFA 06 Soccer",
    "url": "/wiki/FIFA_06",
    "year": 2005,
    "month": 10,
    "day": 4,
    "systems": [
      "Xbox"
    ]
  },
  {
    "title": "FIFA Street",
    "url": "/wiki/FIFA_Street",
    "year": 2005,
    "month": 2,
    "day": 22,
    "systems": [
      "Gamecube",
      "Xbox"
    ]
  },
  {
    "title": "Fight Night Round 2",
    "url": "/wiki/Fight_Night_Round_2",
    "year": 2005,
    "month": 2,
    "day": 28,
    "systems": [
      "Gamecube",
      "Xbox"
    ]
  },
  {
    "title": "FlatOut",
    "url": "/wiki/FlatOut_(video_game)",
    "year": 2005,
    "month": 7,
    "day": 12,
    "systems": [
      "Xbox"
    ]
  },
  {
    "title": "Ford Mustang: The Legend Lives",
    "url": "/wiki/Ford_Mustang:_The_Legend_Lives",
    "year": 2005,
    "month": 4,
    "day": 20,
    "systems": [
      "Xbox"
    ]
  },
  {
    "title": "Ford Racing 3",
    "url": "/wiki/Ford_Racing_3",
    "year": 2005,
    "month": 3,
    "day": 22,
    "systems": [
      "Xbox"
    ]
  },
  {
    "title": "Ford vs. Chevy",
    "url": "/wiki/Ford_vs._Chevy",
    "year": 2005,
    "month": 11,
    "day": 9,
    "systems": [
      "Xbox"
    ]
  },
  {
    "title": "Forza Motorsport",
    "url": "/wiki/Forza_Motorsport",
    "year": 2005,
    "month": 5,
    "day": 3,
    "systems": [
      "Xbox"
    ]
  },
  {
    "title": "Frogger: Ancient Shadow",
    "url": "/wiki/Frogger:_Ancient_Shadow",
    "year": 2005,
    "month": 9,
    "day": 28,
    "systems": [
      "Xbox"
    ]
  },
  {
    "title": "Gauntlet: Seven Sorrows",
    "url": "/wiki/Gauntlet:_Seven_Sorrows",
    "year": 2005,
    "month": 12,
    "day": 12,
    "systems": [
      "Xbox"
    ]
  },
  {
    "title": "Grand Theft Auto: San Andreas",
    "url": "/wiki/Grand_Theft_Auto:_San_Andreas",
    "year": 2005,
    "month": 6,
    "day": 7,
    "systems": [
      "Xbox"
    ]
  },
  {
    "title": "Grand Theft Auto: The Trilogy",
    "url": "/wiki/Grand_Theft_Auto:_The_Trilogy",
    "year": 2005,
    "month": 10,
    "day": 19,
    "systems": [
      "Xbox"
    ]
  },
  {
    "title": "Greg Hastings' Tournament Paintball Max'd",
    "url": "/wiki/Greg_Hastings%27_Tournament_Paintball_Max%27d",
    "year": 2005,
    "month": 10,
    "day": 18,
    "systems": [
      "Xbox"
    ]
  },
  {
    "title": "Gun",
    "url": "/wiki/Gun_(video_game)",
    "year": 2005,
    "month": 11,
    "day": 8,
    "systems": [
      "Xbox"
    ]
  },
  {
    "title": "Half-Life 2",
    "url": "/wiki/Half-Life_2",
    "year": 2005,
    "month": 11,
    "day": 15,
    "systems": [
      "Xbox"
    ]
  },
  {
    "title": "Halo 2 Multiplayer Map Pack",
    "url": "/wiki/Halo_2_Multiplayer_Map_Pack",
    "year": 2005,
    "month": 7,
    "day": 5,
    "systems": [
      "Xbox"
    ]
  },
  {
    "title": "Halo Triple Pack",
    "url": "/wiki/Halo_Triple_Pack",
    "year": 2005,
    "month": 10,
    "day": 6,
    "systems": [
      "Xbox"
    ]
  },
  {
    "title": "Harry Potter and the Goblet of Fire",
    "url": "/wiki/Harry_Potter_and_the_Goblet_of_Fire_(video_game)",
    "year": 2005,
    "month": 11,
    "day": 8,
    "systems": [
      "Gamecube",
      "Xbox"
    ]
  },
  {
    "title": "Heroes of the Pacific",
    "url": "/wiki/Heroes_of_the_Pacific",
    "year": 2005,
    "month": 9,
    "day": 28,
    "systems": [
      "Xbox"
    ]
  },
  {
    "title": "The Incredible Hulk: Ultimate Destruction",
    "url": "/wiki/The_Incredible_Hulk:_Ultimate_Destruction",
    "year": 2005,
    "month": 8,
    "day": 23,
    "systems": [
      "Gamecube",
      "Xbox"
    ]
  },
  {
    "title": "The Incredibles: Rise of the Underminer",
    "url": "/wiki/The_Incredibles:_Rise_of_the_Underminer",
    "year": 2005,
    "month": 11,
    "day": 1,
    "systems": [
      "Gamecube",
      "Xbox"
    ]
  },
  {
    "title": "Indigo Prophecy",
    "url": "/wiki/Indigo_Prophecy",
    "year": 2005,
    "month": 9,
    "day": 20,
    "systems": [
      "Xbox"
    ]
  },
  {
    "title": "Jade Empire",
    "url": "/wiki/Jade_Empire",
    "year": 2005,
    "month": 4,
    "day": 12,
    "systems": [
      "Xbox"
    ]
  },
  {
    "title": "Judge Dredd: Dredd Vs. Death",
    "url": "/wiki/Judge_Dredd:_Dredd_Vs._Death",
    "year": 2005,
    "month": 3,
    "day": 3,
    "systems": [
      "Xbox"
    ]
  },
  {
    "title": "Juiced",
    "url": "/wiki/Juiced_(video_game)",
    "year": 2005,
    "month": 6,
    "day": 13,
    "systems": [
      "Xbox"
    ]
  },
  {
    "title": "Karaoke Revolution Party",
    "url": "/wiki/Karaoke_Revolution",
    "year": 2005,
    "month": 11,
    "day": 8,
    "systems": [
      "Gamecube",
      "Xbox"
    ]
  },
  {
    "title": "Kingdom Under Fire: Heroes",
    "url": "/wiki/Kingdom_Under_Fire:_Heroes",
    "year": 2005,
    "month": 9,
    "day": 20,
    "systems": [
      "Xbox"
    ]
  },
  {
    "title": "The King of Fighters 02/03",
    "url": null,
    "year": 2005,
    "month": 8,
    "day": 30,
    "systems": [
      "Xbox"
    ]
  },
  {
    "title": "L.A. Rush",
    "url": "/wiki/L.A._Rush",
    "year": 2005,
    "month": 10,
    "day": 10,
    "systems": [
      "Xbox"
    ]
  },
  {
    "title": "Land of the Dead: Road to Fiddler's Green",
    "url": "/wiki/Land_of_the_Dead:_Road_to_Fiddler%27s_Green",
    "year": 2005,
    "month": 10,
    "day": 18,
    "systems": [
      "Xbox"
    ]
  },
  {
    "title": "Lego Star Wars: The Video Game",
    "url": "/wiki/Lego_Star_Wars:_The_Video_Game",
    "year": 2005,
    "month": 4,
    "day": 5,
    "systems": [
      "Xbox"
    ]
  },
  {
    "title": "Madagascar",
    "url": "/wiki/Madagascar_(video_game)",
    "year": 2005,
    "month": 5,
    "day": 24,
    "systems": [
      "Gamecube",
      "Xbox"
    ]
  },
  {
    "title": "Madden NFL 06",
    "url": "/wiki/Madden_NFL_06",
    "year": 2005,
    "month": 8,
    "day": 8,
    "systems": [
      "Gamecube",
      "Xbox"
    ]
  },
  {
    "title": "Major League Baseball 2K5",
    "url": "/wiki/Major_League_Baseball_2K5",
    "year": 2005,
    "month": 2,
    "day": 23,
    "systems": [
      "Xbox"
    ]
  },
  {
    "title": "Marvel Nemesis: Rise of the Imperfects",
    "url": "/wiki/Marvel_Nemesis:_Rise_of_the_Imperfects",
    "year": 2005,
    "month": 9,
    "day": 20,
    "systems": [
      "Gamecube",
      "Xbox"
    ]
  },
  {
    "title": "The Matrix: Path of Neo",
    "url": "/wiki/The_Matrix:_Path_of_Neo",
    "year": 2005,
    "month": 11,
    "day": 7,
    "systems": [
      "Xbox"
    ]
  },
  {
    "title": "Medal of Honor: European Assault",
    "url": "/wiki/Medal_of_Honor:_European_Assault",
    "year": 2005,
    "month": 6,
    "day": 7,
    "systems": [
      "Gamecube",
      "Xbox"
    ]
  },
  {
    "title": "Mega Man Anniversary Collection",
    "url": "/wiki/Mega_Man_Anniversary_Collection",
    "year": 2005,
    "month": 3,
    "day": 15,
    "systems": [
      "Xbox"
    ]
  },
  {
    "title": "Mercenaries: Playground of Destruction",
    "url": "/wiki/Mercenaries:_Playground_of_Destruction",
    "year": 2005,
    "month": 1,
    "day": 11,
    "systems": [
      "Xbox"
    ]
  },
  {
    "title": "Midnight Club 3: DUB Edition",
    "url": "/wiki/Midnight_Club_3:_DUB_Edition",
    "year": 2005,
    "month": 4,
    "day": 13,
    "systems": [
      "Xbox"
    ]
  },
  {
    "title": "Midway Arcade Treasures 3",
    "url": "/wiki/Midway_Arcade_Treasures_3",
    "year": 2005,
    "month": 9,
    "day": 26,
    "systems": [
      "Xbox"
    ]
  },
  {
    "title": "Mortal Kombat: Shaolin Monks",
    "url": "/wiki/Mortal_Kombat:_Shaolin_Monks",
    "year": 2005,
    "month": 9,
    "day": 16,
    "systems": [
      "Xbox"
    ]
  },
  {
    "title": "Motocross Mania 3",
    "url": "/wiki/Motocross_Mania_3",
    "year": 2005,
    "month": 4,
    "day": 27,
    "systems": [
      "Xbox"
    ]
  },
  {
    "title": "MotoGP 3",
    "url": "/wiki/MotoGP_3:_Ultimate_Racing_Technology",
    "year": 2005,
    "month": 8,
    "day": 30,
    "systems": [
      "Xbox"
    ]
  },
  {
    "title": "MVP Baseball 2005",
    "url": "/wiki/MVP_Baseball_2005",
    "year": 2005,
    "month": 2,
    "day": 22,
    "systems": [
      "Gamecube",
      "Xbox"
    ]
  },
  {
    "title": "MX vs. ATV Unleashed",
    "url": "/wiki/MX_vs._ATV_Unleashed",
    "year": 2005,
    "month": 3,
    "day": 24,
    "systems": [
      "Xbox"
    ]
  },
  {
    "title": "MX World Tour Featuring Jamie Little",
    "url": null,
    "year": 2005,
    "month": 4,
    "day": 6,
    "systems": [
      "Xbox"
    ]
  },
  {
    "title": "Myst IV: Revelation",
    "url": "/wiki/Myst_IV:_Revelation",
    "year": 2005,
    "month": 3,
    "day": 20,
    "systems": [
      "Xbox"
    ]
  },
  {
    "title": "Namco Museum 50th Anniversary",
    "url": "/wiki/Namco_Museum_50th_Anniversary",
    "year": 2005,
    "month": 8,
    "day": 30,
    "systems": [
      "Gamecube",
      "Xbox"
    ]
  },
  {
    "title": "Narc",
    "url": "/wiki/NARC_(video_game)",
    "year": 2005,
    "month": 5,
    "day": 19,
    "systems": [
      "Xbox"
    ]
  },
  {
    "title": "NASCAR 06: Total Team Control",
    "url": "/wiki/NASCAR_06:_Total_Team_Control",
    "year": 2005,
    "month": 8,
    "day": 30,
    "systems": [
      "Xbox"
    ]
  },
  {
    "title": "NBA 2K6",
    "url": "/wiki/NBA_2K6",
    "year": 2005,
    "month": 9,
    "day": 26,
    "systems": [
      "Xbox"
    ]
  },
  {
    "title": "NBA Live 06",
    "url": "/wiki/NBA_Live_06",
    "year": 2005,
    "month": 9,
    "day": 26,
    "systems": [
      "Gamecube",
      "Xbox"
    ]
  },
  {
    "title": "NBA Street V3",
    "url": "/wiki/NBA_Street_V3",
    "year": 2005,
    "month": 2,
    "day": 8,
    "systems": [
      "Gamecube",
      "Xbox"
    ]
  },
  {
    "title": "NCAA Football 06",
    "url": "/wiki/NCAA_Football_06",
    "year": 2005,
    "month": 7,
    "day": 11,
    "systems": [
      "Xbox"
    ]
  },
  {
    "title": "NCAA March Madness 06",
    "url": "/wiki/NCAA_March_Madness_06",
    "year": 2005,
    "month": 10,
    "day": 11,
    "systems": [
      "Xbox"
    ]
  },
  {
    "title": "Need for Speed: Most Wanted",
    "url": "/wiki/Need_for_Speed:_Most_Wanted_(2005_video_game)",
    "year": 2005,
    "month": 11,
    "day": 15,
    "systems": [
      "Gamecube",
      "Xbox"
    ]
  },
  {
    "title": "NHL 06",
    "url": "/wiki/NHL_06",
    "year": 2005,
    "month": 9,
    "day": 6,
    "systems": [
      "Gamecube",
      "Xbox"
    ]
  },
  {
    "title": "NHL 2K6",
    "url": "/wiki/NHL_2K6",
    "year": 2005,
    "month": 9,
    "day": 6,
    "systems": [
      "Xbox"
    ]
  },
  {
    "title": "Ninja Gaiden Black",
    "url": "/wiki/Ninja_Gaiden_(Xbox)#Ninja_Gaiden_Black",
    "year": 2005,
    "month": 9,
    "day": 20,
    "systems": [
      "Xbox"
    ]
  },
  {
    "title": "ObsCure",
    "url": "/wiki/ObsCure",
    "year": 2005,
    "month": 4,
    "day": 6,
    "systems": [
      "Xbox"
    ]
  },
  {
    "title": "Oddworld: Stranger's Wrath",
    "url": "/wiki/Oddworld:_Stranger%27s_Wrath",
    "year": 2005,
    "month": 1,
    "day": 25,
    "systems": [
      "Xbox"
    ]
  },
  {
    "title": "Operation Flashpoint: Elite",
    "url": "/wiki/Operation_Flashpoint:_Elite",
    "year": 2005,
    "month": 11,
    "day": 8,
    "systems": [
      "Xbox"
    ]
  },
  {
    "title": "Outlaw Tennis",
    "url": "/wiki/Outlaw_Tennis",
    "year": 2005,
    "month": 7,
    "day": 26,
    "systems": [
      "Xbox"
    ]
  },
  {
    "title": "Pac-Man World 3",
    "url": "/wiki/Pac-Man_World_3",
    "year": 2005,
    "month": 11,
    "day": 17,
    "systems": [
      "Gamecube",
      "Xbox"
    ]
  },
  {
    "title": "Pariah",
    "url": "/wiki/Pariah_(video_game)",
    "year": 2005,
    "month": 5,
    "day": 3,
    "systems": [
      "Xbox"
    ]
  },
  {
    "title": "Peter Jackson's King Kong",
    "url": "/wiki/Peter_Jackson%27s_King_Kong:_The_Official_Game_of_the_Movie",
    "year": 2005,
    "month": 11,
    "day": 21,
    "systems": [
      "Xbox"
    ]
  },
  {
    "title": "Phantom Dust",
    "url": "/wiki/Phantom_Dust",
    "year": 2005,
    "month": 3,
    "day": 15,
    "systems": [
      "Xbox"
    ]
  },
  {
    "title": "Playboy: The Mansion",
    "url": "/wiki/Playboy:_The_Mansion",
    "year": 2005,
    "month": 1,
    "day": 25,
    "systems": [
      "Xbox"
    ]
  },
  {
    "title": "Predator: Concrete Jungle",
    "url": "/wiki/Predator:_Concrete_Jungle",
    "year": 2005,
    "month": 4,
    "day": 26,
    "systems": [
      "Xbox"
    ]
  },
  {
    "title": "Prince of Persia: The Two Thrones",
    "url": "/wiki/Prince_of_Persia:_The_Two_Thrones",
    "year": 2005,
    "month": 12,
    "day": 1,
    "systems": [
      "Gamecube",
      "Xbox"
    ]
  },
  {
    "title": "Project Snowblind",
    "url": "/wiki/Project_Snowblind",
    "year": 2005,
    "month": 2,
    "day": 23,
    "systems": [
      "Xbox"
    ]
  },
  {
    "title": "Psychonauts",
    "url": "/wiki/Psychonauts",
    "year": 2005,
    "month": 4,
    "day": 19,
    "systems": [
      "Xbox"
    ]
  },
  {
    "title": "Pump It Up: Exceed",
    "url": "/wiki/Pump_It_Up_(video_game)",
    "year": 2005,
    "month": 8,
    "day": 29,
    "systems": [
      "Xbox"
    ]
  },
  {
    "title": "The Punisher",
    "url": "/wiki/The_Punisher_(2005_video_game)",
    "year": 2005,
    "month": 1,
    "day": 17,
    "systems": [
      "Xbox"
    ]
  },
  {
    "title": "Raze's Hell",
    "url": "/wiki/Raze%27s_Hell",
    "year": 2005,
    "month": 4,
    "day": 21,
    "systems": [
      "Xbox"
    ]
  },
  {
    "title": "Red Ninja: End of Honor",
    "url": "/wiki/Red_Ninja:_End_of_Honor",
    "year": 2005,
    "month": 3,
    "day": 29,
    "systems": [
      "Xbox"
    ]
  },
  {
    "title": "Robots",
    "url": "/wiki/Robots_(2005_video_game)",
    "year": 2005,
    "month": 2,
    "day": 24,
    "systems": [
      "Gamecube",
      "Xbox"
    ]
  },
  {
    "title": "Rugby 2005",
    "url": "/wiki/Rugby_2005",
    "year": 2005,
    "month": 3,
    "day": 8,
    "systems": [
      "Xbox"
    ]
  },
  {
    "title": "Scooby-Doo! Unmasked",
    "url": "/wiki/Scooby-Doo!_Unmasked",
    "year": 2005,
    "month": 9,
    "day": 12,
    "systems": [
      "Gamecube",
      "Xbox"
    ]
  },
  {
    "title": "American McGee Presents: Scrapland",
    "url": "/wiki/American_McGee",
    "year": 2005,
    "month": 2,
    "day": 28,
    "systems": [
      "Xbox"
    ]
  },
  {
    "title": "SeaWorld: Shamu's Deep Sea Adventures",
    "url": "/wiki/SeaWorld:_Shamu%27s_Deep_Sea_Adventures",
    "year": 2005,
    "month": 11,
    "day": 1,
    "systems": [
      "Xbox"
    ]
  },
  {
    "title": "Sega GT Online",
    "url": "/wiki/Sega_GT_Online",
    "year": 2005,
    "month": 11,
    "day": 1,
    "systems": [
      "Xbox"
    ]
  },
  {
    "title": "Serious Sam II",
    "url": "/wiki/Serious_Sam_II",
    "year": 2005,
    "month": 10,
    "day": 11,
    "systems": [
      "Xbox"
    ]
  },
  {
    "title": "Shadow the Hedgehog",
    "url": "/wiki/Shadow_the_Hedgehog_(video_game)",
    "year": 2005,
    "month": 11,
    "day": 15,
    "systems": [
      "Gamecube",
      "Xbox"
    ]
  },
  {
    "title": "Shattered Union",
    "url": "/wiki/Shattered_Union",
    "year": 2005,
    "month": 10,
    "day": 17,
    "systems": [
      "Xbox"
    ]
  },
  {
    "title": "Shrek SuperSlam",
    "url": "/wiki/Shrek_SuperSlam",
    "year": 2005,
    "month": 10,
    "day": 25,
    "systems": [
      "Gamecube",
      "Xbox"
    ]
  },
  {
    "title": "Sid Meier's Pirates!",
    "url": "/wiki/Sid_Meier%27s_Pirates!_(2004_video_game)",
    "year": 2005,
    "month": 7,
    "day": 11,
    "systems": [
      "Xbox"
    ]
  },
  {
    "title": "The Sims 2",
    "url": "/wiki/The_Sims_2_(console_video_game)",
    "year": 2005,
    "month": 10,
    "day": 24,
    "systems": [
      "Gamecube",
      "Xbox"
    ]
  },
  {
    "title": "Sniper Elite",
    "url": "/wiki/Sniper_Elite_(video_game)",
    "year": 2005,
    "month": 10,
    "day": 18,
    "systems": [
      "Xbox"
    ]
  },
  {
    "title": "Spartan: Total Warrior",
    "url": "/wiki/Spartan:_Total_Warrior",
    "year": 2005,
    "month": 10,
    "day": 27,
    "systems": [
      "Gamecube",
      "Xbox"
    ]
  },
  {
    "title": "Special Forces: Nemesis Strike",
    "url": "/wiki/Nemesis_Strike",
    "year": 2005,
    "month": 3,
    "day": 22,
    "systems": [
      "Xbox"
    ]
  },
  {
    "title": "Spikeout: Battle Street",
    "url": "/wiki/Spikeout:_Battle_Street",
    "year": 2005,
    "month": 3,
    "day": 29,
    "systems": [
      "Xbox"
    ]
  },
  {
    "title": "Splat Magazine Renegade Paintball",
    "url": "/wiki/Splat_Magazine_Renegade_Paintball",
    "year": 2005,
    "month": 10,
    "day": 11,
    "systems": [
      "Xbox"
    ]
  },
  {
    "title": "SpongeBob SquarePants: Lights, Camera, Pants!",
    "url": "/wiki/SpongeBob_SquarePants:_Lights,_Camera,_Pants!",
    "year": 2005,
    "month": 10,
    "day": 21,
    "systems": [
      "Gamecube",
      "Xbox"
    ]
  },
  {
    "title": "The SpongeBob SquarePants Movie Game",
    "url": "/wiki/The_SpongeBob_SquarePants_Movie_Game",
    "year": 2005,
    "month": 2,
    "day": 6,
    "systems": [
      "Xbox"
    ]
  },
  {
    "title": "Spy vs. Spy",
    "url": "/wiki/Spy_vs._Spy_(2005_video_game)",
    "year": 2005,
    "month": 4,
    "day": 29,
    "systems": [
      "Xbox"
    ]
  },
  {
    "title": "SSX On Tour",
    "url": "/wiki/SSX_On_Tour",
    "year": 2005,
    "month": 10,
    "day": 11,
    "systems": [
      "Xbox"
    ]
  },
  {
    "title": "Star Wars: Battlefront II",
    "url": "/wiki/Star_Wars:_Battlefront_II_(2005_video_game)",
    "year": 2005,
    "month": 11,
    "day": 1,
    "systems": [
      "Xbox"
    ]
  },
  {
    "title": "Star Wars: Episode III: Revenge of the Sith",
    "url": "/wiki/Star_Wars:_Episode_III_%E2%80%93_Revenge_of_the_Sith_(video_game)",
    "year": 2005,
    "month": 5,
    "day": 4,
    "systems": [
      "Xbox"
    ]
  },
  {
    "title": "Star Wars: Republic Commando",
    "url": "/wiki/Star_Wars:_Republic_Commando",
    "year": 2005,
    "month": 3,
    "day": 1,
    "systems": [
      "Xbox"
    ]
  },
  {
    "title": "Still Life",
    "url": "/wiki/Still_Life_(video_game)",
    "year": 2005,
    "month": 6,
    "day": 6,
    "systems": [
      "Xbox"
    ]
  },
  {
    "title": "Stolen",
    "url": "/wiki/Stolen_(video_game)",
    "year": 2005,
    "month": 4,
    "day": 22,
    "systems": [
      "Xbox"
    ]
  },
  {
    "title": "Street Fighter Anniversary Collection",
    "url": "/wiki/Street_Fighter_Anniversary_Collection",
    "year": 2005,
    "month": 2,
    "day": 22,
    "systems": [
      "Xbox"
    ]
  },
  {
    "title": "Stubbs the Zombie in Rebel Without a Pulse",
    "url": "/wiki/Stubbs_the_Zombie_in_Rebel_Without_a_Pulse",
    "year": 2005,
    "month": 10,
    "day": 18,
    "systems": [
      "Xbox"
    ]
  },
  {
    "title": "The Suffering: Ties That Bind",
    "url": "/wiki/The_Suffering:_Ties_That_Bind",
    "year": 2005,
    "month": 9,
    "day": 26,
    "systems": [
      "Xbox"
    ]
  },
  {
    "title": "Super Monkey Ball Deluxe",
    "url": "/wiki/Super_Monkey_Ball_Deluxe",
    "year": 2005,
    "month": 3,
    "day": 15,
    "systems": [
      "Xbox"
    ]
  },
  {
    "title": "Taito Legends",
    "url": "/wiki/Taito_Legends",
    "year": 2005,
    "month": 10,
    "day": 25,
    "systems": [
      "Xbox"
    ]
  },
  {
    "title": "Tak: The Great Juju Challenge",
    "url": "/wiki/Tak:_The_Great_Juju_Challenge",
    "year": 2005,
    "month": 9,
    "day": 19,
    "systems": [
      "Gamecube",
      "Xbox"
    ]
  },
  {
    "title": "Tecmo Classic Arcade",
    "url": "/wiki/Tecmo_Classic_Arcade",
    "year": 2005,
    "month": 9,
    "day": 13,
    "systems": [
      "Xbox"
    ]
  },
  {
    "title": "Teenage Mutant Ninja Turtles: Mutant Melee",
    "url": "/wiki/Teenage_Mutant_Ninja_Turtles:_Mutant_Melee",
    "year": 2005,
    "month": 3,
    "day": 15,
    "systems": [
      "Xbox"
    ]
  },
  {
    "title": "Teenage Mutant Ninja Turtles 3: Mutant Nightmare",
    "url": "/wiki/Teenage_Mutant_Ninja_Turtles_3:_Mutant_Nightmare",
    "year": 2005,
    "month": 11,
    "day": 1,
    "systems": [
      "Gamecube",
      "Xbox"
    ]
  },
  {
    "title": "Tiger Woods PGA Tour 06",
    "url": "/wiki/Tiger_Woods_PGA_Tour_06",
    "year": 2005,
    "month": 9,
    "day": 20,
    "systems": [
      "Gamecube",
      "Xbox"
    ]
  },
  {
    "title": "Tim Burton's The Nightmare Before Christmas: Oogie's Revenge",
    "url": "/wiki/Tim_Burton%27s_The_Nightmare_Before_Christmas:_Oogie%27s_Revenge",
    "year": 2005,
    "month": 10,
    "day": 10,
    "systems": [
      "Xbox"
    ]
  },
  {
    "title": "TimeSplitters: Future Perfect",
    "url": "/wiki/TimeSplitters:_Future_Perfect",
    "year": 2005,
    "month": 3,
    "day": 21,
    "systems": [
      "Gamecube",
      "Xbox"
    ]
  },
  {
    "title": "Tom Clancy's Ghost Recon 2: Summit Strike",
    "url": "/wiki/Tom_Clancy%27s_Ghost_Recon_2:_Summit_Strike",
    "year": 2005,
    "month": 8,
    "day": 2,
    "systems": [
      "Xbox"
    ]
  },
  {
    "title": "Tom Clancy's Rainbow Six: Lockdown",
    "url": "/wiki/Tom_Clancy%27s_Rainbow_Six:_Lockdown",
    "year": 2005,
    "month": 9,
    "day": 6,
    "systems": [
      "Xbox"
    ]
  },
  {
    "title": "Tom Clancy's Splinter Cell: Chaos Theory",
    "url": "/wiki/Tom_Clancy%27s_Splinter_Cell:_Chaos_Theory",
    "year": 2005,
    "month": 3,
    "day": 31,
    "systems": [
      "Gamecube",
      "Xbox"
    ]
  },
  {
    "title": "Tony Hawk's American Wasteland",
    "url": "/wiki/Tony_Hawk%27s_American_Wasteland",
    "year": 2005,
    "month": 10,
    "day": 18,
    "systems": [
      "Gamecube",
      "Xbox"
    ]
  },
  {
    "title": "Top Gear RPM Tuning",
    "url": "/wiki/RPM_Tuning",
    "year": 2005,
    "month": 2,
    "day": 16,
    "systems": [
      "Xbox"
    ]
  },
  {
    "title": "Tork: Prehistoric Punk",
    "url": "/wiki/Tork:_Prehistoric_Punk",
    "year": 2005,
    "month": 1,
    "day": 12,
    "systems": [
      "Xbox"
    ]
  },
  {
    "title": "Total Overdose: A Gunslinger's Tale in Mexico",
    "url": "/wiki/Total_Overdose:_A_Gunslinger%27s_Tale_in_Mexico",
    "year": 2005,
    "month": 9,
    "day": 27,
    "systems": [
      "Xbox"
    ]
  },
  {
    "title": "True Crime: New York City",
    "url": "/wiki/True_Crime:_New_York_City",
    "year": 2005,
    "month": 11,
    "day": 15,
    "systems": [
      "Gamecube",
      "Xbox"
    ]
  },
  {
    "title": "Ty the Tasmanian Tiger 3: Night of the Quinkan",
    "url": "/wiki/Ty_the_Tasmanian_Tiger_3:_Night_of_the_Quinkan",
    "year": 2005,
    "month": 10,
    "day": 11,
    "systems": [
      "Xbox"
    ]
  },
  {
    "title": "Ultimate Spider-Man",
    "url": "/wiki/Ultimate_Spider-Man_(video_game)",
    "year": 2005,
    "month": 11,
    "day": 22,
    "systems": [
      "Xbox"
    ]
  },
  {
    "title": "Unreal Championship 2: The Liandri Conflict",
    "url": "/wiki/Unreal_Championship_2:_The_Liandri_Conflict",
    "year": 2005,
    "month": 4,
    "day": 18,
    "systems": [
      "Xbox"
    ]
  },
  {
    "title": "Virtual Pool: Tournament Edition",
    "url": "/wiki/Virtual_Pool:_Tournament_Edition",
    "year": 2005,
    "month": 5,
    "day": 11,
    "systems": [
      "Xbox"
    ]
  },
  {
    "title": "Volvo: Drive For Life",
    "url": null,
    "year": 2005,
    "month": 8,
    "day": 18,
    "systems": [
      "Xbox"
    ]
  },
  {
    "title": "Wallace & Gromit: The Curse of the Were-Rabbit",
    "url": "/wiki/Wallace_%26_Gromit:_The_Curse_of_the_Were-Rabbit_(video_game)",
    "year": 2005,
    "month": 9,
    "day": 29,
    "systems": [
      "Xbox"
    ]
  },
  {
    "title": "The Warriors",
    "url": "/wiki/The_Warriors_(video_game)",
    "year": 2005,
    "month": 10,
    "day": 17,
    "systems": [
      "Xbox"
    ]
  },
  {
    "title": "Without Warning",
    "url": "/wiki/Without_Warning_(video_game)",
    "year": 2005,
    "month": 11,
    "day": 1,
    "systems": [
      "Xbox"
    ]
  },
  {
    "title": "World Championship Poker 2: Featuring Howard Lederer",
    "url": "/wiki/World_Championship_Poker:_Featuring_Howard_Lederer_%22All_In%22",
    "year": 2005,
    "month": 11,
    "day": 3,
    "systems": [
      "Xbox"
    ]
  },
  {
    "title": "World Poker Tour",
    "url": null,
    "year": 2005,
    "month": 10,
    "day": 18,
    "systems": [
      "Xbox"
    ]
  },
  {
    "title": "World Series of Poker",
    "url": "/wiki/World_Series_of_Poker_(video_game)",
    "year": 2005,
    "month": 8,
    "day": 31,
    "systems": [
      "Xbox"
    ]
  },
  {
    "title": "World Soccer Winning Eleven 8 International",
    "url": "/wiki/Pro_Evolution_Soccer_4",
    "year": 2005,
    "month": 2,
    "day": 2,
    "systems": [
      "Xbox"
    ]
  },
  {
    "title": "Worms 3D",
    "url": "/wiki/Worms_3D",
    "year": 2005,
    "month": 3,
    "day": 1,
    "systems": [
      "Xbox"
    ]
  },
  {
    "title": "Worms 4: Mayhem",
    "url": "/wiki/Worms_4:_Mayhem",
    "year": 2005,
    "month": 10,
    "day": 4,
    "systems": [
      "Xbox"
    ]
  },
  {
    "title": "Worms Forts: Under Siege",
    "url": "/wiki/Worms_Forts:_Under_Siege",
    "year": 2005,
    "month": 3,
    "day": 15,
    "systems": [
      "Xbox"
    ]
  },
  {
    "title": "WWE WrestleMania 21",
    "url": "/wiki/WWE_WrestleMania_21",
    "year": 2005,
    "month": 4,
    "day": 20,
    "systems": [
      "Xbox"
    ]
  },
  {
    "title": "X-Men Legends II: Rise of Apocalypse",
    "url": "/wiki/X-Men_Legends_II:_Rise_of_Apocalypse",
    "year": 2005,
    "month": 9,
    "day": 20,
    "systems": [
      "Gamecube",
      "Xbox"
    ]
  },
  {
    "title": "Zathura",
    "url": null,
    "year": 2005,
    "month": 10,
    "day": 25,
    "systems": [
      "Xbox"
    ]
  },
  {
    "title": "ZillerNet",
    "url": null,
    "year": 2005,
    "month": 7,
    "day": 10,
    "systems": [
      "Xbox"
    ]
  }
]